{
  "m_GameObject": {
    "m_FileID": 0,
    "m_PathID": -6430146165842029663
  },
  "m_Enabled": 1,
  "m_Script": {
    "m_FileID": 0,
    "m_PathID": -3815917898655550144
  },
  "m_Name": "",
  "targetMeshes": [
    {
      "m_FileID": 0,
      "m_PathID": -8401289572200893345
    }
  ],
  "_weightedMeshList": [
    {
      "mesh": {
        "m_FileID": 0,
        "m_PathID": -689229580272104928
      },
      "frequency": 1,
      "unique": 0
    },
    {
      "mesh": {
        "m_FileID": 0,
        "m_PathID": 6201676484063334465
      },
      "frequency": 1,
      "unique": 0
    }
  ]
}