{
  "m_GameObject": {
    "m_FileID": 0,
    "m_PathID": -1513987439780651440
  },
  "m_Enabled": 1,
  "m_Script": {
    "m_FileID": 0,
    "m_PathID": 763117774672852569
  },
  "m_Name": "",
  "_category": 0,
  "_type": 0,
  "_variant": 0,
  "_cellSpanX": 3,
  "_cellSpanY": 2,
  "_cellSpanZ": 8,
  "_frontSideMeshFilters": [],
  "_frontSideWallrunMeshFilters": [],
  "_leftSideMeshFilters": [],
  "_leftSideWallrunStartMeshFilters": [],
  "_leftSideWallrunMeshFilters": [],
  "_rightSideMeshFilters": [],
  "_rightSideWallrunStartMeshFilters": [],
  "_rightSideWallrunMeshFilters": [],
  "_laneEndingPieceMeshFilters": [],
  "_otherMeshFilters": [
    {
      "m_FileID": 0,
      "m_PathID": 1902351438907564926
    },
    {
      "m_FileID": 0,
      "m_PathID": 7044520650971996490
    }
  ],
  "_decorationRandomizers": [
    {
      "m_FileID": 0,
      "m_PathID": -9018187448230037346
    }
  ],
  "_meshCombined": 1
}