{
  "m_GameObject": {
    "m_FileID": 0,
    "m_PathID": 1452596249594710976
  },
  "m_Enabled": 1,
  "m_Script": {
    "m_FileID": 0,
    "m_PathID": -4362543063090646589
  },
  "m_Name": "",
  "_abilityInfoDialog": {
    "m_FileID": 0,
    "m_PathID": -533765710657435527
  },
  "_abilityUpgradeSlotPrefab": {
    "m_FileID": 1,
    "m_PathID": 3980665653768479500
  },
  "_pivot": 0,
  "_slotGrid": {
    "m_FileID": 0,
    "m_PathID": 8586866537595987988
  },
  "_sizeWidget": {
    "m_FileID": 0,
    "m_PathID": 8670549440719042107
  },
  "_fullyUpgradedStateSwitcher": {
    "m_FileID": 0,
    "m_PathID": -5538547367775608042
  },
  "_showUpgradeBars": 1
}